[
  {
    "serial_number": 1,
    "participant1_name": "Chandran S",
    "participant2_name": "reshma",
    "team_name": "Core Experience"
  },
  {
    "serial_number": 2,
    "participant1_name": "Keerthana A",
    "participant2_name": "Dharshini",
    "team_name": "SDL"
  },
  {
    "serial_number": 3,
    "participant1_name": "Hari prasad",
    "participant2_name": "Balu",
    "team_name": "SDL"
  },
  {
    "serial_number": 4,
    "participant1_name": "Akash Chandran",
    "participant2_name": "Mohanram",
    "team_name": "Vega"
  },
  {
    "serial_number": 5,
    "participant1_name": "Sudharshan",
    "participant2_name": "Dhanush",
    "team_name": "SE"
  },
  {
    "serial_number": 6,
    "participant1_name": "Syed S",
    "participant2_name": "kaushik",
    "team_name": "3P Launches"
  },
  {
    "serial_number": 7,
    "participant1_name": "Hariharan C",
    "participant2_name": "Sathish Kumar",
    "team_name": "Vega"
  },
  {
    "serial_number": 8,
    "participant1_name": "Harish",
    "participant2_name": "Mirunalini",
    "team_name": "Vega"
  },
  {
    "serial_number": 9,
    "participant1_name": "Ijaz",
    "participant2_name": "chandru",
    "team_name": "SDL"
  },
  {
    "serial_number": 10,
    "participant1_name": "Balaji Giri",
    "participant2_name": "Deepak Kumar",
    "team_name": "Discovery"
  },
  {
    "serial_number": 11,
    "participant1_name": "Muralidharan M",
    "participant2_name": "Akash R",
    "team_name": "System Experience"
  },
  {
    "serial_number": 12,
    "participant1_name": "Muthu",
    "participant2_name": "Susan",
    "team_name": "Discovery"
  },
  {
    "serial_number": 13,
    "participant1_name": "Sakthivel",
    "participant2_name": "sriram",
    "team_name": "SDL"
  },
  {
    "serial_number": 14,
    "participant1_name": "Satish",
    "participant2_name": "Soumya",
    "team_name": "SE"
  },
  {
    "serial_number": 15,
    "participant1_name": "Vignesh",
    "participant2_name": "Sudalai",
    "team_name": "System Experience"
  },
  {
    "serial_number": 16,
    "participant1_name": "Thirumal",
    "participant2_name": "Abirajan",
    "team_name": "Discovery"
  },
  {
    "serial_number": 17,
    "participant1_name": "Dilip",
    "participant2_name": "Kishore",
    "team_name": "Core Experience"
  },
  {
    "serial_number": 18,
    "participant1_name": "Stalin",
    "participant2_name": "Elavarasan",
    "team_name": "3P Apps"
  },
  {
    "serial_number": 19,
    "participant1_name": "Shanmugapriyan",
    "participant2_name": "Karthickraja",
    "team_name": "3P Apps"
  },
  {
    "serial_number": 20,
    "participant1_name": "Akshay",
    "participant2_name": "Hamirth",
    "team_name": "3P Apps"
  },
  {
    "serial_number": 21,
    "participant1_name": "Atshara",
    "participant2_name": "Suriya",
    "team_name": "3P Apps"
  },
  {
    "serial_number": 22,
    "participant1_name": "Hemanth",
    "participant2_name": "Anish",
    "team_name": "SE"
  },
  {
    "serial_number": 23,
    "participant1_name": "Karthik, Anantha",
    "participant2_name": "Shahid Mohammed",
    "team_name": "1P Launches"
  }
]